slack_magic/__init__.py
slack_magic/slack_magic.py
slack_magic-0.0.3.dist-info/AUTHORS.rst
slack_magic-0.0.3.dist-info/LICENSE.txt
slack_magic-0.0.3.dist-info/METADATA
slack_magic-0.0.3.dist-info/WHEEL
slack_magic-0.0.3.dist-info/top_level.txt
slack_magic-0.0.3.dist-info/RECORD
