Metadata-Version: 2.1
Name: slack-magic
Version: 0.0.3
Summary: Notify yourself via slack when lines or cells finish or error out.
Home-page: https://github.com/evanr70/slack_magic
Author: Evan
Author-email: evan.roberts@kellogg.ox.ac.uk
License: mit
Platform: any
Classifier: Development Status :: 4 - Beta
Classifier: Programming Language :: Python
Classifier: Framework :: IPython
Requires-Dist: ipython
Provides-Extra: testing
Requires-Dist: pytest ; extra == 'testing'
Requires-Dist: pytest-cov ; extra == 'testing'
